{
  "temperature": 0.9,
  "downfall": 0,
  "has_precipitation": false,
  "effects": {
    "sky_color": 7842047,
    "fog_color": 12638463,
    "water_color": 4159204,
    "water_fog_color": 329011,
    "mood_sound": {
      "sound": "minecraft:ambient.cave",
      "tick_delay": 6000,
      "block_search_extent": 8,
      "offset": 2
    }
  },
  "spawners": {
    "water_ambient": [
      {
        "type": "minecraft:squid",
        "weight": 20,
        "minCount": 0,
        "maxCount": 1
      },
      {
        "type": "minecraft:glow_squid",
        "weight": 20,
        "minCount": 0,
        "maxCount": 1
      }
    ],
    "ambient": [
      {
        "type": "minecraft:bat",
        "weight": 10,
        "minCount": 0,
        "maxCount": 3
      }
    ]
  },
  "spawn_costs": {},
  "carvers": {
    "air": [
      "minecraft:cave",
      "minecraft:canyon"
    ]
  },
  "features": [
    [],
    [],
    [
      "minecraft:large_dripstone"
    ],
    [],
    [],
    [],
    [
      "minecraft:ore_coal_upper",
      "minecraft:ore_coal_lower",
      "minecraft:ore_iron_upper",
      "minecraft:ore_iron_middle",
      "minecraft:ore_iron_small",
      "minecraft:ore_gold",
      "minecraft:ore_gold_lower",
      "minecraft:ore_redstone",
      "minecraft:ore_redstone_lower",
      "minecraft:ore_diamond",
      "minecraft:ore_diamond_medium",
      "minecraft:ore_diamond_large",
      "minecraft:ore_diamond_buried",
      "minecraft:ore_lapis",
      "minecraft:ore_lapis_buried",
      "minecraft:ore_copper"
    ],
    [
      "minecraft:dripstone_cluster",
      "minecraft:pointed_dripstone"
    ],
    [
      "minecraft:spring_water",
      "minecraft:spring_lava"
    ],
    [
      "minecraft:glow_lichen"
    ],
    [
      "minecraft:freeze_top_layer"
    ]
  ]
}